[{"model": "admin.logentry", "pk": 1, "fields": {"action_time": "2026-06-24T18:31:34.050Z", "user": 1, "content_type": 7, "object_id": "1", "object_repr": "Toys", "action_flag": 1, "change_message": "[{\"added\": {}}]"}}, {"model": "admin.logentry", "pk": 2, "fields": {"action_time": "2026-06-24T18:31:39.643Z", "user": 1, "content_type": 7, "object_id": "2", "object_repr": "Food", "action_flag": 1, "change_message": "[{\"added\": {}}]"}}, {"model": "admin.logentry", "pk": 3, "fields": {"action_time": "2026-06-24T18:31:58.841Z", "user": 1, "content_type": 8, "object_id": "1", "object_repr": "Water pistol", "action_flag": 1, "change_message": "[{\"added\": {}}]"}}, {"model": "admin.logentry", "pk": 4, "fields": {"action_time": "2026-06-24T18:32:15.337Z", "user": 1, "content_type": 8, "object_id": "2", "object_repr": "Plastic flower", "action_flag": 1, "change_message": "[{\"added\": {}}]"}}, {"model": "admin.logentry", "pk": 5, "fields": {"action_time": "2026-06-24T18:32:31.385Z", "user": 1, "content_type": 8, "object_id": "3", "object_repr": "Burger", "action_flag": 1, "change_message": "[{\"added\": {}}]"}}, {"model": "admin.logentry", "pk": 6, "fields": {"action_time": "2026-06-24T18:32:44.190Z", "user": 1, "content_type": 8, "object_id": "4", "object_repr": "Apple", "action_flag": 1, "change_message": "[{\"added\": {}}]"}}, {"model": "admin.logentry", "pk": 7, "fields": {"action_time": "2026-06-24T18:32:52.170Z", "user": 1, "content_type": 9, "object_id": "1", "object_repr": "Review for Apple", "action_flag": 1, "change_message": "[{\"added\": {}}]"}}, {"model": "admin.logentry", "pk": 8, "fields": {"action_time": "2026-06-24T18:33:00.026Z", "user": 1, "content_type": 9, "object_id": "2", "object_repr": "Review for Burger", "action_flag": 1, "change_message": "[{\"added\": {}}]"}}, {"model": "admin.logentry", "pk": 9, "fields": {"action_time": "2026-06-24T18:33:07.825Z", "user": 1, "content_type": 9, "object_id": "3", "object_repr": "Review for Water pistol", "action_flag": 1, "change_message": "[{\"added\": {}}]"}}, {"model": "admin.logentry", "pk": 10, "fields": {"action_time": "2026-06-24T18:33:13.412Z", "user": 1, "content_type": 9, "object_id": "4", "object_repr": "Review for Plastic flower", "action_flag": 1, "change_message": "[{\"added\": {}}]"}}, {"model": "admin.logentry", "pk": 11, "fields": {"action_time": "2026-06-28T13:09:28.355Z", "user": 1, "content_type": 9, "object_id": "4", "object_repr": "Review for Plastic flower", "action_flag": 2, "change_message": "[{\"changed\": {\"fields\": [\"Stars\"]}}]"}}, {"model": "admin.logentry", "pk": 12, "fields": {"action_time": "2026-06-28T13:09:33.056Z", "user": 1, "content_type": 9, "object_id": "3", "object_repr": "Review for Water pistol", "action_flag": 2, "change_message": "[{\"changed\": {\"fields\": [\"Stars\"]}}]"}}, {"model": "admin.logentry", "pk": 13, "fields": {"action_time": "2026-06-28T13:09:37.631Z", "user": 1, "content_type": 9, "object_id": "2", "object_repr": "Review for Burger", "action_flag": 2, "change_message": "[{\"changed\": {\"fields\": [\"Stars\"]}}]"}}, {"model": "admin.logentry", "pk": 14, "fields": {"action_time": "2026-06-28T13:09:43.051Z", "user": 1, "content_type": 9, "object_id": "1", "object_repr": "Review for Apple", "action_flag": 2, "change_message": "[{\"changed\": {\"fields\": [\"Stars\"]}}]"}}, {"model": "admin.logentry", "pk": 15, "fields": {"action_time": "2026-06-28T13:09:58.271Z", "user": 1, "content_type": 9, "object_id": "5", "object_repr": "Review for Water pistol", "action_flag": 1, "change_message": "[{\"added\": {}}]"}}, {"model": "admin.logentry", "pk": 16, "fields": {"action_time": "2026-06-28T13:10:06.045Z", "user": 1, "content_type": 9, "object_id": "6", "object_repr": "Review for Water pistol", "action_flag": 1, "change_message": "[{\"added\": {}}]"}}, {"model": "admin.logentry", "pk": 17, "fields": {"action_time": "2026-06-28T13:10:15.508Z", "user": 1, "content_type": 9, "object_id": "7", "object_repr": "Review for Plastic flower", "action_flag": 1, "change_message": "[{\"added\": {}}]"}}, {"model": "admin.logentry", "pk": 18, "fields": {"action_time": "2026-06-28T13:10:23.944Z", "user": 1, "content_type": 9, "object_id": "8", "object_repr": "Review for Plastic flower", "action_flag": 1, "change_message": "[{\"added\": {}}]"}}, {"model": "admin.logentry", "pk": 19, "fields": {"action_time": "2026-06-28T13:10:32.926Z", "user": 1, "content_type": 9, "object_id": "9", "object_repr": "Review for Burger", "action_flag": 1, "change_message": "[{\"added\": {}}]"}}, {"model": "admin.logentry", "pk": 20, "fields": {"action_time": "2026-06-28T13:10:40.104Z", "user": 1, "content_type": 9, "object_id": "10", "object_repr": "Review for Burger", "action_flag": 1, "change_message": "[{\"added\": {}}]"}}, {"model": "admin.logentry", "pk": 21, "fields": {"action_time": "2026-06-28T13:10:49.284Z", "user": 1, "content_type": 9, "object_id": "11", "object_repr": "Review for Apple", "action_flag": 1, "change_message": "[{\"added\": {}}]"}}, {"model": "admin.logentry", "pk": 22, "fields": {"action_time": "2026-06-28T13:10:58.067Z", "user": 1, "content_type": 9, "object_id": "12", "object_repr": "Review for Apple", "action_flag": 1, "change_message": "[{\"added\": {}}]"}}, {"model": "auth.user", "pk": 1, "fields": {"password": "pbkdf2_sha256$1200000$wPGzskcjoFOlY5m8NJWFrI$bPATrm8q6nJldhWDFZZt/Msi9dAm4H0IjHL7HtppbnE=", "last_login": "2026-07-02T10:00:12.611Z", "is_superuser": true, "username": "nazar", "first_name": "", "last_name": "", "email": "", "is_staff": true, "is_active": true, "date_joined": "2026-06-24T18:30:58.394Z", "groups": [], "user_permissions": []}}, {"model": "auth.user", "pk": 2, "fields": {"password": "pbkdf2_sha256$1200000$EYwb3X7421QM2Msj6ZKZdM$ait2h7L8/xm1acHzuTWnAWGi3ACYrMDvcUHrlq1vC/U=", "last_login": null, "is_superuser": false, "username": "hwcheck2", "first_name": "", "last_name": "", "email": "hwcheck2@example.com", "is_staff": false, "is_active": true, "date_joined": "2026-07-09T12:54:43.145Z", "groups": [], "user_permissions": []}}, {"model": "sessions.session", "pk": "6te9rznxi58zmbb9ni7btnxmzh8w0hb0", "fields": {"session_data": ".eJxVjEEOwiAQRe_C2hAG2gFcuvcMBGZAqoYmpV0Z765NutDtf-_9lwhxW2vYel7CxOIsQJx-txTpkdsO-B7bbZY0t3WZktwVedAurzPn5-Vw_w5q7PVb02ghOWbjCnE0qaDNyjMqoEyWedAKEli0xEYBsvOGBm0QNbBPZRTvD_xhN_8:1wcSNf:uel7RgaOj81Mdu7Nyag671yRWwta8NEjh_hqeG0jedQ", "expire_date": "2026-07-08T18:31:23.520Z"}}, {"model": "sessions.session", "pk": "dzeem29g3zgn5lmfwkm1ckn6zehwum8r", "fields": {"session_data": ".eJxVjEEOwiAQRe_C2hAG2gFcuvcMBGZAqoYmpV0Z765NutDtf-_9lwhxW2vYel7CxOIsQJx-txTpkdsO-B7bbZY0t3WZktwVedAurzPn5-Vw_w5q7PVb02ghOWbjCnE0qaDNyjMqoEyWedAKEli0xEYBsvOGBm0QNbBPZRTvD_xhN_8:1wfEDM:tIG8YFgQin2EBKyB-X2q2ht49dRIegdhptsAsofA2Qg", "expire_date": "2026-07-16T10:00:12.618Z"}}, {"model": "sessions.session", "pk": "l5r1q88zd4gz2uef4fkpxhduh0352ajk", "fields": {"session_data": ".eJxVjEEOwiAQRe_C2hAG2gFcuvcMBGZAqoYmpV0Z765NutDtf-_9lwhxW2vYel7CxOIsQJx-txTpkdsO-B7bbZY0t3WZktwVedAurzPn5-Vw_w5q7PVb02ghOWbjCnE0qaDNyjMqoEyWedAKEli0xEYBsvOGBm0QNbBPZRTvD_xhN_8:1wdpDU:0rqkIQgRu1RhMShRxBNNRcn7SmDMdQeap8OvN40sQBA", "expire_date": "2026-07-12T13:06:32.582Z"}}, {"model": "product.category", "pk": 1, "fields": {"name": "Toys"}}, {"model": "product.category", "pk": 2, "fields": {"name": "Food"}}, {"model": "product.category", "pk": 3, "fields": {"name": "cars"}}, {"model": "product.product", "pk": 1, "fields": {"title": "Water pistol", "description": "yes", "price": 56, "category": 1}}, {"model": "product.product", "pk": 2, "fields": {"title": "Plastic flower", "description": "more", "price": 2, "category": 1}}, {"model": "product.product", "pk": 3, "fields": {"title": "Burger", "description": "mmm", "price": 30, "category": 2}}, {"model": "product.product", "pk": 4, "fields": {"title": "Apple", "description": "yuk", "price": 1, "category": 2}}, {"model": "product.review", "pk": 1, "fields": {"text": "nono", "product": 4, "stars": 4}}, {"model": "product.review", "pk": 2, "fields": {"text": "yesyes", "product": 3, "stars": 3}}, {"model": "product.review", "pk": 3, "fields": {"text": "shoot", "product": 1, "stars": 1}}, {"model": "product.review", "pk": 4, "fields": {"text": "smell", "product": 2, "stars": 5}}, {"model": "product.review", "pk": 5, "fields": {"text": "aaaaaaaaaaaaa", "product": 1, "stars": 1}}, {"model": "product.review", "pk": 6, "fields": {"text": "agg", "product": 1, "stars": 3}}, {"model": "product.review", "pk": 7, "fields": {"text": "nuh", "product": 2, "stars": 4}}, {"model": "product.review", "pk": 8, "fields": {"text": "nuyf", "product": 2, "stars": 5}}, {"model": "product.review", "pk": 9, "fields": {"text": "qwerty", "product": 3, "stars": 5}}, {"model": "product.review", "pk": 10, "fields": {"text": "ass", "product": 3, "stars": 1}}, {"model": "product.review", "pk": 11, "fields": {"text": "dance", "product": 4, "stars": 2}}, {"model": "product.review", "pk": 12, "fields": {"text": "ncifije", "product": 4, "stars": 1}}]
